mypackage/__init__.py
mypackage/mymodule.py
tests/__init__.py
tests/test_mymodule.py
julim_package-0.1.5.dist-info/LICENSE
julim_package-0.1.5.dist-info/METADATA
julim_package-0.1.5.dist-info/WHEEL
julim_package-0.1.5.dist-info/top_level.txt
julim_package-0.1.5.dist-info/RECORD
