Metadata-Version: 2.1
Name: julim_package
Version: 0.1.5
Summary: 공부해라
Home-page: https://github.com/koesnuj/python_study
Author: julim
Author-email: whizkid00@gmail.com
Classifier: Programming Language :: Python :: 3
Classifier: License :: OSI Approved :: MIT License
Classifier: Operating System :: OS Independent
Requires-Python: >=3.6
License-File: LICENSE
